django_notes/__init__.py
django_notes/admin.py
django_notes/apps.py
django_notes/models.py
django_notes/tests.py
django_notes/urls.py
django_notes/views.py
django_notes/migrations/0001_initial.py
django_notes/migrations/__init__.py
django_notes/templates/note/index.html
krid_notes-0.2.dist-info/METADATA
krid_notes-0.2.dist-info/WHEEL
krid_notes-0.2.dist-info/top_level.txt
krid_notes-0.2.dist-info/RECORD
